src/__init_.py
src/kindle2pdf.py
src/pdf2remarkable.py
src/utils.py
kindle2pdf-0.5.4.dist-info/LICENSE
kindle2pdf-0.5.4.dist-info/METADATA
kindle2pdf-0.5.4.dist-info/WHEEL
kindle2pdf-0.5.4.dist-info/entry_points.txt
kindle2pdf-0.5.4.dist-info/RECORD
