Metadata-Version: 2.1
Name: kindle2pdf
Version: 0.5.4
Summary: 
Author: Robert Dargavel Smith
Author-email: teticio@gmail.com
Requires-Python: >=3.10,<4.0
Classifier: Programming Language :: Python :: 3
Classifier: Programming Language :: Python :: 3.10
Classifier: Programming Language :: Python :: 3.11
Classifier: Programming Language :: Python :: 3.12
Classifier: Programming Language :: Python :: 3.13
Requires-Dist: browser-cookie3 (>=0.20.1,<0.21.0)
Requires-Dist: cryptography (>=42.0.5,<43.0.0)
Requires-Dist: pypdf (>=5.0.1,<6.0.0)
Requires-Dist: reportlab (>=4.1.0,<5.0.0)
Requires-Dist: requests (>=2.31.0,<3.0.0)
Requires-Dist: svglib (>=1.5.1,<2.0.0)
Requires-Dist: tqdm (>=4.66.2,<5.0.0)
